{
    "last_operation": "average",
    "last_column": "rate",
    "history": [
        {
            "ts": "2025-09-10T22:20:57",
            "query": "average of sttl",
            "result": "np.float64(180.96766749259098)",
            "used_context": false
        },
        {
            "ts": "2025-09-10T22:21:04",
            "query": "of dur",
            "result": "np.float64(1.0067561463464996)",
            "used_context": true
        },
        {
            "ts": "2025-09-10T22:21:08",
            "query": "of rate",
            "result": "np.float64(82410.88673910811)",
            "used_context": true
        }
    ]
}